LICENSE.rst
MANIFEST.in
README.rst
setup.cfg
setup.py
dtool_config/__init__.py
dtool_config/cli.py
dtool_config/utils.py
dtool_config.egg-info/PKG-INFO
dtool_config.egg-info/SOURCES.txt
dtool_config.egg-info/dependency_links.txt
dtool_config.egg-info/entry_points.txt
dtool_config.egg-info/requires.txt
dtool_config.egg-info/top_level.txt