Metadata-Version: 1.1
Name: dtool-config
Version: 0.4.1
Summary: Plugin to make configuration of dtool easier
Home-page: https://github.com/jic-dtool/dtool-config
Author: Tjelvar Olsson
Author-email: tjelvar.olsson@gmail.com
License: MIT
Download-URL: https://github.com/jic-dtool/dtool-config/tarball/0.4.1
Platform: UNKNOWN
